globadoo/chat.py
globadoo/client.py
globadoo/find_country.py
globadoo/main.py
globadoo/models.py
globadoo/prompt.py
globadoo-0.1.1.dist-info/entry_points.txt
globadoo-0.1.1.dist-info/WHEEL
globadoo-0.1.1.dist-info/METADATA
globadoo-0.1.1.dist-info/RECORD
